flask_wikimediaui/__init__.py
flask_wikimediaui/functions.py
flask_wikimediaui/static/.git
flask_wikimediaui/static/My Wikimedia Project.html
flask_wikimediaui/static/components.html
flask_wikimediaui/static/index.html
flask_wikimediaui/static/MW/Gruntfile.js
flask_wikimediaui/static/MW/custom-theme.less
flask_wikimediaui/static/MW/custom-variables.less
flask_wikimediaui/static/MW/elements.html
flask_wikimediaui/static/MW/icons.svg
flask_wikimediaui/static/MW/mediawiki.css
flask_wikimediaui/static/MW/mediawiki.less
flask_wikimediaui/static/MW/mediawiki.min.css
flask_wikimediaui/static/MW/svg4everybody.min.js
flask_wikimediaui/static/MW/webcomponents.min.js
flask_wikimediaui/static/assets/button.svg
flask_wikimediaui/static/assets/card.svg
flask_wikimediaui/static/assets/colors.svg
flask_wikimediaui/static/assets/dropdown.svg
flask_wikimediaui/static/assets/header.svg
flask_wikimediaui/static/assets/icons.svg
flask_wikimediaui/static/assets/images.svg
flask_wikimediaui/static/assets/input-group.svg
flask_wikimediaui/static/assets/layouts.svg
flask_wikimediaui/static/assets/list.svg
flask_wikimediaui/static/assets/panel.svg
flask_wikimediaui/static/assets/pill.svg
flask_wikimediaui/static/assets/prism.css
flask_wikimediaui/static/assets/prism.js
flask_wikimediaui/static/assets/snippet.css
flask_wikimediaui/static/assets/snippets.js
flask_wikimediaui/static/assets/tab.svg
flask_wikimediaui/static/assets/typography.svg
flask_wikimediaui/static/bootstrap-3.3.5-dist/css/bootstrap-theme.css
flask_wikimediaui/static/bootstrap-3.3.5-dist/css/bootstrap-theme.css.map
flask_wikimediaui/static/bootstrap-3.3.5-dist/css/bootstrap-theme.min.css
flask_wikimediaui/static/bootstrap-3.3.5-dist/css/bootstrap.css
flask_wikimediaui/static/bootstrap-3.3.5-dist/css/bootstrap.css.map
flask_wikimediaui/static/bootstrap-3.3.5-dist/css/bootstrap.min.css
flask_wikimediaui/static/bootstrap-3.3.5-dist/css/docs.min.css
flask_wikimediaui-0.0.1.dist-info/DESCRIPTION.rst
flask_wikimediaui-0.0.1.dist-info/METADATA
flask_wikimediaui-0.0.1.dist-info/RECORD
flask_wikimediaui-0.0.1.dist-info/WHEEL
flask_wikimediaui-0.0.1.dist-info/metadata.json
flask_wikimediaui-0.0.1.dist-info/top_level.txt
