Metadata-Version: 1.1
Name: flask-wikimediaui
Version: 0.0.1
Summary: This library provides python Flask utilities and static assets for rendering Wikimedia UI elements
Home-page: http://pypi.python.org/pypi/flask-wikimediaui
Author: Aaron Halfaker
Author-email: aaron.halfaker@gmail.com
License: The MIT License (MIT)
